core/__init__.py
core/mail_proxy/__init__.py
core/mail_proxy/proxy.py
core/mail_proxy/proxy_base.py
core/mail_proxy/proxy_config.py
core/mail_proxy/py.typed
core/mail_proxy/server.py
core/mail_proxy/entities/__init__.py
core/mail_proxy/entities/account/README.md
core/mail_proxy/entities/account/__init__.py
core/mail_proxy/entities/account/endpoint.py
core/mail_proxy/entities/account/table.py
core/mail_proxy/entities/command_log/__init__.py
core/mail_proxy/entities/command_log/endpoint.py
core/mail_proxy/entities/command_log/table.py
core/mail_proxy/entities/instance/__init__.py
core/mail_proxy/entities/instance/endpoint.py
core/mail_proxy/entities/instance/table.py
core/mail_proxy/entities/message/README.md
core/mail_proxy/entities/message/__init__.py
core/mail_proxy/entities/message/endpoint.py
core/mail_proxy/entities/message/table.py
core/mail_proxy/entities/message_event/__init__.py
core/mail_proxy/entities/message_event/table.py
core/mail_proxy/entities/storage/__init__.py
core/mail_proxy/entities/storage/endpoint.py
core/mail_proxy/entities/storage/table.py
core/mail_proxy/entities/tenant/README.md
core/mail_proxy/entities/tenant/__init__.py
core/mail_proxy/entities/tenant/endpoint.py
core/mail_proxy/entities/tenant/table.py
core/mail_proxy/interface/__init__.py
core/mail_proxy/interface/api_base.py
core/mail_proxy/interface/cli_base.py
core/mail_proxy/interface/cli_commands.py
core/mail_proxy/interface/endpoint_base.py
core/mail_proxy/interface/forms.py
core/mail_proxy/reporting/__init__.py
core/mail_proxy/reporting/client_reporter.py
core/mail_proxy/smtp/__init__.py
core/mail_proxy/smtp/attachments.py
core/mail_proxy/smtp/cache.py
core/mail_proxy/smtp/pool.py
core/mail_proxy/smtp/rate_limiter.py
core/mail_proxy/smtp/retry.py
core/mail_proxy/smtp/sender.py
enterprise/__init__.py
enterprise/mail_proxy/__init__.py
enterprise/mail_proxy/proxy_ee.py
enterprise/mail_proxy/attachments/__init__.py
enterprise/mail_proxy/attachments/large_file_storage.py
genro_mail_proxy-0.7.0.dist-info/METADATA
genro_mail_proxy-0.7.0.dist-info/WHEEL
genro_mail_proxy-0.7.0.dist-info/entry_points.txt
genro_mail_proxy-0.7.0.dist-info/licenses/LICENSE
genro_mail_proxy-0.7.0.dist-info/licenses/LICENSE-BSL-1.1
genro_mail_proxy-0.7.0.dist-info/licenses/NOTICE
genro_mail_proxy-0.7.0.dist-info/RECORD
