Metadata-Version: 2.4
Name: genro-mail-proxy
Version: 0.7.0
Summary: Asynchronous email dispatcher microservice with scheduling, rate limiting, attachments, and a FastAPI REST API.
Project-URL: Homepage, https://github.com/genropy/genro-mail-proxy
Project-URL: Documentation, https://genro-mail-proxy.readthedocs.io
Project-URL: Repository, https://github.com/genropy/genro-mail-proxy
Project-URL: Issues, https://github.com/genropy/genro-mail-proxy/issues
Author-email: Genropy Team <info@genropy.org>
License-Expression: Apache-2.0
License-File: LICENSE
License-File: LICENSE-BSL-1.1
License-File: NOTICE
Keywords: async,email,fastapi,genro,genropy,mail-proxy,smtp
Classifier: Development Status :: 4 - Beta
Classifier: Framework :: FastAPI
Classifier: Intended Audience :: Developers
Classifier: Operating System :: OS Independent
Classifier: Programming Language :: Python :: 3
Classifier: Programming Language :: Python :: 3.10
Classifier: Programming Language :: Python :: 3.11
Classifier: Programming Language :: Python :: 3.12
Classifier: Programming Language :: Python :: 3.13
Classifier: Topic :: Communications :: Email
Classifier: Topic :: Internet :: WWW/HTTP :: HTTP Servers
Classifier: Topic :: Software Development :: Libraries :: Application Frameworks
Classifier: Typing :: Typed
Requires-Python: >=3.10
Requires-Dist: aiohttp>=3.9.0
Requires-Dist: aiosmtplib>=2.0.0
Requires-Dist: aiosqlite>=0.20.0
Requires-Dist: click>=8.1.0
Requires-Dist: fastapi>=0.115.0
Requires-Dist: genro-toolbox>=0.1.0
Requires-Dist: prometheus-client>=0.20.0
Requires-Dist: pydantic>=2.8.0
Requires-Dist: requests>=2.31.0
Requires-Dist: rich>=13.0.0
Requires-Dist: uvicorn>=0.30.0
Provides-Extra: all
Requires-Dist: adlfs>=2024.1.0; extra == 'all'
Requires-Dist: aioimaplib>=1.0.0; extra == 'all'
Requires-Dist: aioresponses>=0.7.0; extra == 'all'
Requires-Dist: aiosmtpd>=1.4.0; extra == 'all'
Requires-Dist: bandit>=1.7.0; extra == 'all'
Requires-Dist: cryptography>=41.0.0; extra == 'all'
Requires-Dist: gcsfs>=2024.1.0; extra == 'all'
Requires-Dist: httpx>=0.27.0; extra == 'all'
Requires-Dist: mypy>=1.0; extra == 'all'
Requires-Dist: myst-parser>=4.0.0; extra == 'all'
Requires-Dist: psycopg-pool>=3.1.0; extra == 'all'
Requires-Dist: psycopg[binary]>=3.1.0; extra == 'all'
Requires-Dist: pytest-asyncio>=0.23.0; extra == 'all'
Requires-Dist: pytest-cov>=4.0; extra == 'all'
Requires-Dist: pytest-docker>=3.0.0; extra == 'all'
Requires-Dist: pytest>=8.0; extra == 'all'
Requires-Dist: ruff>=0.1.0; extra == 'all'
Requires-Dist: s3fs>=2024.1.0; extra == 'all'
Requires-Dist: sphinx-autodoc-typehints>=3.0.0; extra == 'all'
Requires-Dist: sphinx-rtd-theme>=3.0.0; extra == 'all'
Requires-Dist: sphinx>=8.0.0; extra == 'all'
Requires-Dist: sphinxcontrib-mermaid>=1.0.0; extra == 'all'
Requires-Dist: testcontainers[postgres]>=4.0.0; extra == 'all'
Provides-Extra: dev
Requires-Dist: aioresponses>=0.7.0; extra == 'dev'
Requires-Dist: aiosmtpd>=1.4.0; extra == 'dev'
Requires-Dist: bandit>=1.7.0; extra == 'dev'
Requires-Dist: cryptography>=41.0.0; extra == 'dev'
Requires-Dist: httpx>=0.27.0; extra == 'dev'
Requires-Dist: mypy>=1.0; extra == 'dev'
Requires-Dist: pytest-asyncio>=0.23.0; extra == 'dev'
Requires-Dist: pytest-cov>=4.0; extra == 'dev'
Requires-Dist: pytest-docker>=3.0.0; extra == 'dev'
Requires-Dist: pytest>=8.0; extra == 'dev'
Requires-Dist: ruff>=0.1.0; extra == 'dev'
Requires-Dist: testcontainers[postgres]>=4.0.0; extra == 'dev'
Provides-Extra: docs
Requires-Dist: myst-parser>=4.0.0; extra == 'docs'
Requires-Dist: sphinx-autodoc-typehints>=3.0.0; extra == 'docs'
Requires-Dist: sphinx-rtd-theme>=3.0.0; extra == 'docs'
Requires-Dist: sphinx>=8.0.0; extra == 'docs'
Requires-Dist: sphinxcontrib-mermaid>=1.0.0; extra == 'docs'
Provides-Extra: enterprise
Requires-Dist: adlfs>=2024.1.0; extra == 'enterprise'
Requires-Dist: aioimaplib>=1.0.0; extra == 'enterprise'
Requires-Dist: gcsfs>=2024.1.0; extra == 'enterprise'
Requires-Dist: psycopg-pool>=3.1.0; extra == 'enterprise'
Requires-Dist: psycopg[binary]>=3.1.0; extra == 'enterprise'
Requires-Dist: s3fs>=2024.1.0; extra == 'enterprise'
Provides-Extra: enterprise-azure
Requires-Dist: adlfs>=2024.1.0; extra == 'enterprise-azure'
Provides-Extra: enterprise-gcs
Requires-Dist: gcsfs>=2024.1.0; extra == 'enterprise-gcs'
Provides-Extra: enterprise-s3
Requires-Dist: s3fs>=2024.1.0; extra == 'enterprise-s3'
Provides-Extra: postgresql
Requires-Dist: psycopg-pool>=3.1.0; extra == 'postgresql'
Requires-Dist: psycopg[binary]>=3.1.0; extra == 'postgresql'
